{"name":"MarkDown","slug":"MarkDown","count":1,"postlist":[{"title":"MarkDown公式书写","uid":"2929836d59d95692b6043d49510b51db","slug":"MarkDown公式书写","date":"2022-05-23T13:56:54.000Z","updated":"2022-05-23T13:58:11.222Z","comments":true,"path":"api/articles/MarkDown公式书写.json","keywords":null,"cover":[],"text":"MarkDown公式书写 一般公式分为两种形式，行内公式和行间公式。 行内公式： 行间公式： 对应的代码块为： $ \\Gamma(z) &#x3D; \\int_0^\\infty t^&#123;z-1&#125;e^&#123;-t&#125;dt\\,. $ $$\\Gamma(z...","link":"","photos":[],"count_time":{"symbolsCount":"9k","symbolsTime":"8 mins."},"categories":[],"tags":[{"name":"MarkDown","slug":"MarkDown","count":1,"path":"api/tags/MarkDown.json"}],"author":{"name":"YingHN","slug":"blog-author","avatar":"https://s2.loli.net/2022/12/24/vS8KdpjE9WVInX2.jpg","link":"/","description":"","socials":{"github":"","twitter":"","stackoverflow":"","wechat":"","qq":"","weibo":"","zhihu":"","csdn":"","juejin":"","customs":{}}}}]}