{"name":"Math","slug":"Math","count":2,"postlist":[{"title":"线性代数（2）-- 基、线性组合与线性变换","uid":"204e43540bf8202442012df009ee58c9","slug":"线性代数（2）-- 基、线性组合与线性变换","date":"2022-05-01T10:09:01.000Z","updated":"2022-05-01T10:14:33.199Z","comments":true,"path":"api/articles/线性代数（2）-- 基、线性组合与线性变换.json","keywords":null,"cover":[],"text":"线性代数（2）– 基、线性组合与线性变换基引入如果把 向量坐标 看作 标量 ，整个向量看作 矩阵 ，也就是说，将 向量 看作对 基 进行缩放，就可以做很多有趣的事 定义几个个 沿着坐标轴 的 向量 ，长度为 一，能成线性组合任意向量 将 X轴 上的 基 叫做 Î ， 读作i-ha...","link":"","photos":[],"count_time":{"symbolsCount":447,"symbolsTime":"1 mins."},"categories":[],"tags":[{"name":"Math","slug":"Math","count":2,"path":"api/tags/Math.json"}],"author":{"name":"YingHN","slug":"blog-author","avatar":"https://img-blog.csdnimg.cn/20210313122054101.png","link":"/","description":"","socials":{"github":"","twitter":"","stackoverflow":"","wechat":"","qq":"","weibo":"","zhihu":"","csdn":"","juejin":"","customs":{}}},"feature":true},{"title":"线性代数（1）-- 向量","uid":"47f169f6526decd8e42c6eeb5bc1fc29","slug":"线性代数（1）-- 向量","date":"2022-05-01T10:06:54.000Z","updated":"2022-05-01T10:11:56.520Z","comments":true,"path":"api/articles/线性代数（1）-- 向量.json","keywords":null,"cover":[],"text":"线性代数（1）– 向量向量的定义：一条带箭头的线段 向量的表示：以原点O为起点，用箭头末端的坐标表示，用方括号[]括住。 如图： 向量加法表示以其中一个向量的终点为起点，叠加另一个向量。 如图： 那么新向量是什么呢？只要__对应坐标相加__即可，如图： 向量乘法向量不能与向量相乘...","link":"","photos":[],"count_time":{"symbolsCount":200,"symbolsTime":"1 mins."},"categories":[],"tags":[{"name":"Math","slug":"Math","count":2,"path":"api/tags/Math.json"}],"author":{"name":"YingHN","slug":"blog-author","avatar":"https://img-blog.csdnimg.cn/20210313122054101.png","link":"/","description":"","socials":{"github":"","twitter":"","stackoverflow":"","wechat":"","qq":"","weibo":"","zhihu":"","csdn":"","juejin":"","customs":{}}},"feature":true}]}